llm_costs/__init__.py
llm_costs/calculator.py
llm_costs/models.py
llm_costs/pricing/anthropic.yaml
llm_costs/pricing/google.yaml
llm_costs/pricing/openai.yaml
llm_costs/providers/__init__.py
llm_costs/providers/anthropic.py
llm_costs/providers/google.py
llm_costs/providers/openai.py
llm_costs-0.1.2.dist-info/METADATA
llm_costs-0.1.2.dist-info/WHEEL
llm_costs-0.1.2.dist-info/RECORD
