Metadata-Version: 2.4
Name: llm-costs
Version: 0.1.2
Summary: LLM cost calculator for major providers
Author-email: jason <jtan92@gmail.com>
Requires-Python: >=3.13
Requires-Dist: pyyaml>=6.0
Provides-Extra: dev
Requires-Dist: pytest>=8.0; extra == 'dev'
Requires-Dist: ruff>=0.8; extra == 'dev'
